wav_loo/__init__.py
wav_loo/cli.py
wav_loo/finder.py
wav_loo/data_gen/__init__.py
wav_loo/data_gen/generator.py
wav_loo/loss/__init__.py
wav_loo/loss/multi_channel_separation_consistency_loss.py
wav_loo/noise/__init__.py
wav_loo/noise/segments.py
wav_loo/utils/__init__.py
wav_loo/utils/audio.py
wav_loo/utils/constants.py
wav_loo/utils/ir_utils.py
wav_loo-1.3.0.dist-info/licenses/LICENSE
wav_loo-1.3.0.dist-info/METADATA
wav_loo-1.3.0.dist-info/WHEEL
wav_loo-1.3.0.dist-info/entry_points.txt
wav_loo-1.3.0.dist-info/top_level.txt
wav_loo-1.3.0.dist-info/RECORD
