Metadata-Version: 2.4
Name: wav-loo
Version: 1.3.0
Summary: A multi-tool: WAV finder, multi-zone data generator (2/4 zones, multi-channel IR), and CLI aliases
Home-page: https://github.com/ioyy900205/loolang_tools
Author: liuliang
Author-email: liuliang <ioyy900205@gmail.com>
License: MIT
Project-URL: Homepage, https://github.com/ioyy900205/loolang_tools
Project-URL: Repository, https://github.com/ioyy900205/loolang_tools
Classifier: Development Status :: 3 - Alpha
Classifier: Intended Audience :: Developers
Classifier: License :: OSI Approved :: MIT License
Classifier: Operating System :: OS Independent
Classifier: Programming Language :: Python :: 3
Classifier: Programming Language :: Python :: 3.7
Classifier: Programming Language :: Python :: 3.8
Classifier: Programming Language :: Python :: 3.9
Classifier: Programming Language :: Python :: 3.10
Classifier: Programming Language :: Python :: 3.11
Requires-Python: >=3.7
License-File: LICENSE
Requires-Dist: requests>=2.25.0
Requires-Dist: beautifulsoup4>=4.9.0
Requires-Dist: urllib3>=1.26.0
Requires-Dist: soundfile>=0.12.1
Requires-Dist: scipy>=1.10.0
Dynamic: author
Dynamic: home-page
Dynamic: license-file
Dynamic: requires-python
